py4web_debug/__about__.py
py4web_debug/__init__.py
py4web_debug/_internals.py
py4web_debug/core.py
py4web_debug/debugbar.py
py4web_debug/dumping.py
py4web_debug/env.py
py4web_debug/internals.py
py4web_debug/py.typed
py4web_debug/types.py
py4web_debug/wsgi.py
py4web_debug/templates/debugbar.html
py4web_debug/templates/dumpdie.html
py4web_debug/templates/error_default.html
py4web_debug/templates/fancy_dumpdie.html
py4web_debug_tools-1.3.2.dist-info/METADATA
py4web_debug_tools-1.3.2.dist-info/WHEEL
py4web_debug_tools-1.3.2.dist-info/RECORD
