Metadata-Version: 2.4
Name: py4web-debug-tools
Version: 1.3.2
Summary: Debug Tools for py4web
Project-URL: Documentation, https://github.com/trialandsuccess/py4web-debug-tools#readme
Project-URL: Issues, https://github.com/trialandsuccess/py4web-debug-tools/issues
Project-URL: Source, https://github.com/trialandsuccess/py4web-debug-tools
Author-email: Robin van der Noord <contact@trialandsuccess.nl>
License-Expression: MIT
Classifier: Development Status :: 4 - Beta
Classifier: Programming Language :: Python
Classifier: Programming Language :: Python :: 3.10
Classifier: Programming Language :: Python :: 3.11
Classifier: Programming Language :: Python :: 3.12
Classifier: Programming Language :: Python :: Implementation :: CPython
Classifier: Programming Language :: Python :: Implementation :: PyPy
Requires-Python: >=3.10
Requires-Dist: configurable-json>=1.1
Requires-Dist: py4web
Requires-Dist: pydal
Requires-Dist: typing-extensions
Requires-Dist: yatl
Provides-Extra: dev
Requires-Dist: hatch; extra == 'dev'
Requires-Dist: su6[all]; extra == 'dev'
